globus_action_provider_tools/__init__.py
globus_action_provider_tools/action_request.yaml
globus_action_provider_tools/action_status.yaml
globus_action_provider_tools/authentication.py
globus_action_provider_tools/authorization.py
globus_action_provider_tools/client_factory.py
globus_action_provider_tools/data_types.py
globus_action_provider_tools/errors.py
globus_action_provider_tools/flask/__init__.py
globus_action_provider_tools/flask/apt_blueprint.py
globus_action_provider_tools/flask/config.py
globus_action_provider_tools/flask/exceptions.py
globus_action_provider_tools/flask/helpers.py
globus_action_provider_tools/flask/request_lifecycle_hooks/__init__.py
globus_action_provider_tools/flask/request_lifecycle_hooks/cloudwatch_metrics.py
globus_action_provider_tools/flask/types.py
globus_action_provider_tools/storage.py
globus_action_provider_tools/utils.py
globus_action_provider_tools/validation.py
globus_action_provider_tools-0.20.1.dist-info/LICENSE
globus_action_provider_tools-0.20.1.dist-info/METADATA
globus_action_provider_tools-0.20.1.dist-info/WHEEL
globus_action_provider_tools-0.20.1.dist-info/entry_points.txt
globus_action_provider_tools-0.20.1.dist-info/RECORD
