Metadata-Version: 2.1
Name: globus-action-provider-tools
Version: 0.20.1
Summary: Tools to help developers build services that implement the Action Provider specification.
License: Apache-2.0
Keywords: globus,automation,workflow,action_provider
Author: Globus Team
Author-email: support@globus.org
Requires-Python: >=3.8
Classifier: Development Status :: 4 - Beta
Classifier: Intended Audience :: Developers
Classifier: License :: Free To Use But Restricted
Classifier: License :: OSI Approved :: Apache Software License
Classifier: Programming Language :: Python :: 3
Classifier: Programming Language :: Python :: 3.8
Classifier: Programming Language :: Python :: 3.9
Classifier: Programming Language :: Python :: 3.10
Classifier: Programming Language :: Python :: 3.11
Classifier: Programming Language :: Python :: 3.12
Classifier: Programming Language :: Python :: 3.13
Classifier: Topic :: Internet :: WWW/HTTP
Classifier: Topic :: Software Development :: Libraries :: Application Frameworks
Classifier: Topic :: Software Development :: Libraries :: Python Modules
Provides-Extra: flask
Requires-Dist: cachetools (>=5.0,<6.0)
Requires-Dist: flask (>=2.3.0,<3.0.0) ; extra == "flask"
Requires-Dist: globus-sdk (>=3.9.0,<4.0.0)
Requires-Dist: isodate (>=0.6.0,<0.7.0)
Requires-Dist: jsonschema (>=4.17,<5.0)
Requires-Dist: pydantic (>=1.7.3,<2.0.0)
Requires-Dist: pyyaml (>=6,<7)
